pyne_script/__init__.py
pyne_script/series.py
pyne_script_utilities-1.0.5.dist-info/LICENSE
pyne_script_utilities-1.0.5.dist-info/METADATA
pyne_script_utilities-1.0.5.dist-info/WHEEL
pyne_script_utilities-1.0.5.dist-info/top_level.txt
pyne_script_utilities-1.0.5.dist-info/RECORD
