Metadata-Version: 2.1
Name: pyne-script-utilities
Version: 1.0.5
Summary: A set of utility sub-modules that allow for code structure similar to pinescript in python
Author: 80sVectorz
Project-URL: Homepage, https://github.com/80sVectorz/pyne_script
Project-URL: Bug Tracker, https://github.com/80sVectorz/pyne_script/issues
Classifier: Programming Language :: Python :: 3
Classifier: License :: OSI Approved :: GNU General Public License v3 (GPLv3)
Requires-Python: >=3.10
License-File: LICENSE
Requires-Dist: numpy
